SQLike.py
SQLike-1.0.0.dist-info/LICENSE
SQLike-1.0.0.dist-info/METADATA
SQLike-1.0.0.dist-info/WHEEL
SQLike-1.0.0.dist-info/top_level.txt
SQLike-1.0.0.dist-info/RECORD
